<?xml version="1.0"?>
<root>
  <item>
    <name>fn+hjkl and fn+o for enter</name>
    <identifier>private.hjkl_and_o</identifier>
    <autogen>
      __KeyToKey__
      KeyCode::H, ModifierFlag::FN,
      KeyCode::CURSOR_LEFT
    </autogen>

    <autogen>
      __KeyToKey__
      KeyCode::J, ModifierFlag::FN,
      KeyCode::CURSOR_DOWN
    </autogen>

    <autogen>
      __KeyToKey__
      KeyCode::K, ModifierFlag::FN,
      KeyCode::CURSOR_UP
    </autogen>

    <autogen>
      __KeyToKey__
      KeyCode::L, ModifierFlag::FN,
      KeyCode::CURSOR_RIGHT
    </autogen>

    <autogen>
      __KeyToKey__
      KeyCode::O, ModifierFlag::FN,
      KeyCode::ENTER
    </autogen>
  </item>

</root>
